competitorx/__init__.py
competitorx/main.py
competitorx-1.0.dist-info/LICENSE
competitorx-1.0.dist-info/METADATA
competitorx-1.0.dist-info/WHEEL
competitorx-1.0.dist-info/top_level.txt
competitorx-1.0.dist-info/RECORD
