Metadata-Version: 2.1
Name: competitorx
Version: 1.0
Author-email: Sike Brothers <sikebros@gmail.com>
Classifier: Programming Language :: Python :: 3
Classifier: License :: OSI Approved :: MIT License
Classifier: Operating System :: OS Independent
Requires-Python: >=3
License-File: LICENSE
